setup.py
pytest_multithreading_allure/__init__.py
pytest_multithreading_allure.egg-info/PKG-INFO
pytest_multithreading_allure.egg-info/SOURCES.txt
pytest_multithreading_allure.egg-info/dependency_links.txt
pytest_multithreading_allure.egg-info/entry_points.txt
pytest_multithreading_allure.egg-info/requires.txt
pytest_multithreading_allure.egg-info/top_level.txt