Metadata-Version: 2.1
Name: pytest-multithreading-allure
Version: 1.0.5
Summary: pytest_multithreading_allure
Author: zhujiahuan
Author-email: zhujiahuan@yfcloud.com
License: MIT
Platform: UNKNOWN
